scooterbot_agent/__init__.py
scooterbot_agent/agent.py
scooterbot_agent/private_agent.py
scooterbot_agent/python_api_agent.py
scooterbot_agent-3.0.1.dist-info/LICENSE
scooterbot_agent-3.0.1.dist-info/METADATA
scooterbot_agent-3.0.1.dist-info/WHEEL
scooterbot_agent-3.0.1.dist-info/RECORD
